LICENSE
pymongo_inmemory/__init__.py
pymongo_inmemory/_pim.py
pymongo_inmemory/_utils.py
pymongo_inmemory/context.py
pymongo_inmemory/downloader/__init__.py
pymongo_inmemory/downloader/__main__.py
pymongo_inmemory/downloader/_patterns.py
pymongo_inmemory/downloader/_urls.py
pymongo_inmemory/mongod.py
pymongo_inmemory-0.4.2.dist-info/LICENSE
pymongo_inmemory-0.4.2.dist-info/METADATA
pymongo_inmemory-0.4.2.dist-info/WHEEL
pymongo_inmemory-0.4.2.dist-info/RECORD
