Metadata-Version: 2.1
Name: pymongo_inmemory
Version: 0.4.2
Summary: A mongo mocking library with an ephemeral MongoDB running in memory.
Home-page: https://github.com/kaizendorks/pymongo_inmemory
License: MIT
Keywords: mongodb,testing,pymongo
Author: Kaizen Dorks
Author-email: kaizendorks@gmail.com
Maintainer: Ertugrul Karademir
Maintainer-email: ekarademir@gmail.com
Requires-Python: >=3.9,<4.0
Classifier: Development Status :: 3 - Alpha
Classifier: Intended Audience :: Developers
Classifier: License :: OSI Approved :: MIT License
Classifier: Operating System :: MacOS :: MacOS X
Classifier: Operating System :: Microsoft :: Windows
Classifier: Operating System :: POSIX :: Linux
Classifier: Programming Language :: Python :: 3
Classifier: Programming Language :: Python :: 3.9
Classifier: Programming Language :: Python :: 3.10
Classifier: Programming Language :: Python :: 3.11
Classifier: Programming Language :: Python :: 3.12
Classifier: Programming Language :: Python :: 3.7
Classifier: Topic :: Database :: Database Engines/Servers
Classifier: Topic :: Software Development :: Testing
Classifier: Topic :: Utilities
Requires-Dist: pymongo
Project-URL: Bug Reports, https://github.com/kaizendorks/pymongo_inmemory/issues
Project-URL: Repository, https://github.com/kaizendorks/pymongo_inmemory
